{
  "updated": "2026-03-09 10:52 JST",
  "count": 3,
  "news": [
    {
      "title": "＼予約受付3月9日(月)まで／ 🍓ラブライブ！シリーズ15周年記念グッズ🍓 BIGアクリルスタンド【全60種】予約受付中✨ 🎈μ's 🎈Aqours 🎈虹ヶ咲学園スクールアイドル同好会 🎈Liella! 🎈スクールアイドルミュージカル 🎈蓮ノ空女学院スクールアイドルクラブ https://lovelive-series-schoolstore.bnfw.jp/lovelive15th/index.html #lovelive",
      "link": "https://nitter.net/LoveLive_staff/status/2030527686045798611#m",
      "published": "2026-03-08 15:15 JST",
      "is_retweet": false
    },
    {
      "title": "☀CD情報☀ ラブライブ！サンシャイン!! #Aqours Finale LoveLive! ～永久stage～ LIVE CD 3/11(水)発売🎉 Day.2公演のライブ音源に加えて、日替わり楽曲を収録🎵 ご予約はこちら🔽 http://lnk.to/LACA-19170 店舗別特典はこちら🔽 https://lovelive-anime.jp/news/01_5625.html ぜひゲットしてください🎵 #lovelive",
      "link": "https://nitter.net/LoveLive_staff/status/2030508813888205038#m",
      "published": "2026-03-08 14:00 JST",
      "is_retweet": false
    },
    {
      "title": "☀️CD情報☀️ 3月11日(水)発売 GKSSシングル「WAKE:WOKE」/「BURN:BORN」 Guilty Kiss × Saint Snow TWO-MAN LIVE CD先行抽選（最速）申込券を封入✨ ご予約はこちら🔽 【Guilty Kiss盤】 http://lnk.to/LACM-24830 【Saint Snow盤】 http://lnk.to/LACM-24831 #lovelive #GKSS",
      "link": "https://nitter.net/LoveLive_staff/status/2030501264073617617#m",
      "published": "2026-03-08 13:30 JST",
      "is_retweet": false
    }
  ]
}